notion_tqdm/__init__.py
notion_tqdm/constants.py
notion_tqdm/std.py
notion_tqdm-0.2.0.dist-info/LICENSE
notion_tqdm-0.2.0.dist-info/METADATA
notion_tqdm-0.2.0.dist-info/WHEEL
notion_tqdm-0.2.0.dist-info/top_level.txt
notion_tqdm-0.2.0.dist-info/RECORD
